cftdeploy/__init__.py
cftdeploy/_version.py
cftdeploy/entry_points.py
cftdeploy/manifest.py
cftdeploy/skeleton.py
cftdeploy/stack.py
cftdeploy/template.py
cftdeploy-1.0.7.dist-info/LICENSE
cftdeploy-1.0.7.dist-info/METADATA
cftdeploy-1.0.7.dist-info/WHEEL
cftdeploy-1.0.7.dist-info/entry_points.txt
cftdeploy-1.0.7.dist-info/top_level.txt
cftdeploy-1.0.7.dist-info/RECORD
