Metadata-Version: 2.1
Name: cftdeploy
Version: 1.0.7
Summary: Tools and modules for managing CloudFormation Templates & Stacks
Home-page: http://github.com/jchrisfarris/cft-deploy
Author: Chris Farris
Author-email: chris@room17.com
License: Apache License 2.0
Requires-Python: >=3.6
License-File: LICENSE
Requires-Dist: boto3 (>=1.10.0)
Requires-Dist: botocore (>=1.13.0)
Requires-Dist: pyyaml
